botdoc/__init__.py
botdoc-102.data/data/share/doc/botdoc/about.rst
botdoc-102.data/data/share/doc/botdoc/admin.rst
botdoc-102.data/data/share/doc/botdoc/base.rst
botdoc-102.data/data/share/doc/botdoc/botd2.png
botdoc-102.data/data/share/doc/botdoc/botdgreensmile.png
botdoc-102.data/data/share/doc/botdoc/botdline.jpg
botdoc-102.data/data/share/doc/botdoc/botlib.css
botdoc-102.data/data/share/doc/botdoc/botlib.jpg
botdoc-102.data/data/share/doc/botdoc/botlib2.jpg
botdoc-102.data/data/share/doc/botdoc/botlib3.jpg
botdoc-102.data/data/share/doc/botdoc/botlibwall.jpg
botdoc-102.data/data/share/doc/botdoc/class.rst
botdoc-102.data/data/share/doc/botdoc/conf.py
botdoc-102.data/data/share/doc/botdoc/index.rst
botdoc-102.data/data/share/doc/botdoc/layout.html
botdoc-102.data/data/share/doc/botdoc/module.rst
botdoc-102.data/data/share/doc/botdoc/programmer.rst
botdoc-102.data/data/share/doc/botdoc/source.rst
botdoc-102.data/data/share/doc/botdoc/_static/botlib.css
botdoc-102.data/data/share/doc/botdoc/_templates/base.rst
botdoc-102.data/data/share/doc/botdoc/_templates/class.rst
botdoc-102.data/data/share/doc/botdoc/_templates/layout.html
botdoc-102.data/data/share/doc/botdoc/_templates/module.rst
botdoc-102.dist-info/METADATA
botdoc-102.dist-info/WHEEL
botdoc-102.dist-info/top_level.txt
botdoc-102.dist-info/RECORD
