Metadata-Version: 2.1
Name: botdoc
Version: 102
Summary: The Python3 bot Namespace
Home-page: https://github.com/bthate/botdoc
Author: Bart Thate
Author-email: bthate67@gmail.com
License: Public Domain
Classifier: Development Status :: 4 - Beta
Classifier: License :: Public Domain
Classifier: Operating System :: Unix
Classifier: Programming Language :: Python
Classifier: Topic :: Utilities
Requires-Dist: botd
Requires-Dist: botlib
